MANIFEST.in
README.md
setup.py
bin/calc_ionograms
bin/detect_chirps
bin/plot_ionograms
bin/plot_rf_spec
src/ChirpSounder.egg-info/PKG-INFO
src/ChirpSounder.egg-info/SOURCES.txt
src/ChirpSounder.egg-info/dependency_links.txt
src/ChirpSounder.egg-info/requires.txt
src/ChirpSounder.egg-info/top_level.txt
src/chirpsounder/__init__.py
src/chirpsounder/calc_ionograms.py
src/chirpsounder/chirp_config.py
src/chirpsounder/chirp_det.py
src/chirpsounder/chirp_lib.py
src/chirpsounder/crop_ionograms.py
src/chirpsounder/detect_chirps.py
src/chirpsounder/fast_exp.py
src/chirpsounder/find_timings.py
src/chirpsounder/gps_sensors.py
src/chirpsounder/odin.py
src/chirpsounder/plot_ionograms.py
src/chirpsounder/plot_rf_spec.py
src/chirpsounder/thor_simple.py
src/chirpsounder/cSources/Makefile
src/chirpsounder/cSources/chirp_downconvert.c
src/chirpsounder/cSources/chirp_downconvert.h
src/chirpsounder/cSources/rx_uhd.cpp