Metadata-Version: 2.1
Name: ChirpSounder
Version: 2.0.4
Summary: Detect chirp sounders and over the horizon transmissions
Home-page: UNKNOWN
Author: Juha Vierinen
Author-email: juha-pekka.vierinen@uit.no
License: UNKNOWN
Platform: UNKNOWN
Classifier: Development Status :: 4 - Beta
Classifier: Intended Audience :: Science/Research
Classifier: Natural Language :: English
Classifier: Programming Language :: Python :: 3
Requires-Python: >=3.6
